[
	{ "s": "Я", "p": [795, 660, 943, 445, 947, 740, 739, 738, 714, 676, 971, 1037, 977, 685, 794, 761, 753, 674, 991, 983, 981, 980, 880, 837, 792, 752, 713, 679, 677, 448, 405, 171, 111] },
	{ "s": "Я-БУФЕР", "p": [111] },
	{ "s": "ЯБЛОК", "p": [1039, 1010, 951, 946] },
	{ "s": "ЯБЛОКА", "p": [1039, 954, 951, 620] },
	{ "s": "ЯБЛОКИ", "p": [953, 620] },
	{ "s": "ЯБЛОКО", "p": [955, 620] },
	{ "s": "ЯБЛОКОМ", "p": [1039, 953, 951] },
	{ "s": "ЯВИЛА", "p": [339] },
	{ "s": "ЯВЛЕНИЕ", "p": [795, 417, 407, 357, 351, 168, 33, 5] },
	{ "s": "ЯВЛЕНИЕМ", "p": [692, 330] },
	{ "s": "ЯВЛЕНИЙ", "p": [414, 314] },
	{ "s": "ЯВЛЕНИЯ", "p": [1018, 1017, 1002, 633, 391, 242, 236, 235, 215, 205] },
	{ "s": "ЯВЛЯЕТСЯ", "p": [315, 140, 677, 628, 114, 52, 996, 977, 954, 692, 669, 607, 407, 400, 391, 362, 301, 271, 227, 224, 181, 166, 144, 143, 97, 86, 76, 71, 70, 69, 68, 42, 1061, 1037, 1033, 1030, 1028, 967, 907, 879, 876, 776, 744, 738, 732, 694, 691, 679, 662, 660, 615, 583, 556, 471, 462, 449, 444, 441, 433, 381, 379, 361, 358, 356, 352, 351, 348, 340, 316, 287, 274, 262, 228, 205, 179, 178, 175, 160, 152, 139, 136, 112, 111, 101, 98, 55, 54, 53, 43] },
	{ "s": "ЯВЛЯЛА", "p": [676] },
	{ "s": "ЯВЛЯЛАСЬ", "p": [11, 7] },
	{ "s": "ЯВЛЯЛИ", "p": [999] },
	{ "s": "ЯВЛЯЛОСЬ", "p": [633] },
	{ "s": "ЯВЛЯЛСЯ", "p": [1047, 938] },
	{ "s": "ЯВЛЯТЬСЯ", "p": [637, 594, 529, 254] },
	{ "s": "ЯВЛЯЮТСЯ", "p": [740, 738, 677, 437, 301, 262, 252, 1061, 996, 992, 970, 923, 915, 884, 800, 739, 676, 603, 503, 394, 379, 308, 276, 235, 221, 219, 216, 101, 74, 68, 43, 33, 15, 5] },
	{ "s": "ЯВЛЯЮЩЕЕСЯ", "p": [660] },
	{ "s": "ЯВЛЯЮЩИХСЯ", "p": [628] },
	{ "s": "ЯВНО", "p": [928, 777, 774, 607, 452, 341, 315, 305, 81, 21, 1060, 1047, 1038, 1034, 905, 884, 822, 799, 760, 754, 746, 682, 661, 554, 456, 351, 348, 340, 286, 250, 209, 203, 118, 88, 54, 53] },
	{ "s": "ЯВНОГО", "p": [191] },
	{ "s": "ЯВНОЕ", "p": [44] },
	{ "s": "ЯВНОЙ", "p": [593] },
	{ "s": "ЯВНЫЕ", "p": [836, 475, 52] },
	{ "s": "ЯВНЫЙ", "p": [807, 628] },
	{ "s": "ЯВНЫМ", "p": [804] },
	{ "s": "ЯВНЫХ", "p": [290] },
	{ "s": "ЯВСТВЕННЕЕ", "p": [444] },
	{ "s": "ЯГОД", "p": [42] },
	{ "s": "ЯГОДАМИ", "p": [42] },
	{ "s": "ЯГРУМ", "p": [70, 308] },
	{ "s": "ЯГРУМА", "p": [70] },
	{ "s": "ЯДЕР", "p": [787] },
	{ "s": "ЯДЕРНЫЙ", "p": [959] },
	{ "s": "ЯДЕРНЫХ", "p": [799] },
	{ "s": "ЯДОМ", "p": [53] },
	{ "s": "ЯДРАМИ", "p": [787] },
	{ "s": "ЯДРО", "p": [53] },
	{ "s": "ЯДУ", "p": [795] },
	{ "s": "ЯЗЫК", "p": [946, 479, 795, 715, 712, 677, 622, 542, 300, 218, 28] },
	{ "s": "ЯЗЫКА", "p": [676, 802, 700, 675] },
	{ "s": "ЯЗЫКЕ", "p": [795, 707, 677, 676] },
	{ "s": "ЯЗЫКОВ", "p": [727, 676, 22] },
	{ "s": "ЯЗЫКОВОЙ", "p": [837] },
	{ "s": "ЯЗЫКОМ", "p": [679] },
	{ "s": "ЯЙЦО", "p": [52] },
	{ "s": "ЯКОРЕМ", "p": [52] },
	{ "s": "ЯКОРЬ", "p": [53] },
	{ "s": "ЯКОРЯМИ", "p": [966, 964] },
	{ "s": "ЯМЫ", "p": [1059] },
	{ "s": "ЯНВАРЯ", "p": [445, 5] },
	{ "s": "ЯПОНСКАЯ", "p": [24] },
	{ "s": "ЯПОНЦАМ", "p": [29] },
	{ "s": "ЯРКАЯ", "p": [1007, 346] },
	{ "s": "ЯРКИЕ", "p": [439, 21] },
	{ "s": "ЯРКИЙ", "p": [987, 739, 623, 439, 426, 360, 346, 343, 315, 299, 113] },
	{ "s": "ЯРКИМ", "p": [880, 612, 444, 343, 330] },
	{ "s": "ЯРКИМИ", "p": [600, 569] },
	{ "s": "ЯРКО", "p": [880, 608, 593, 343, 330] },
	{ "s": "ЯРКОГО", "p": [799] },
	{ "s": "ЯРКОЕ", "p": [955, 340, 298, 193, 131, 30] },
	{ "s": "ЯРКОЙ", "p": [1037, 880, 878] },
	{ "s": "ЯРКОМ", "p": [879] },
	{ "s": "ЯРКОСТИ", "p": [443, 880, 433, 1041, 1038, 879, 803, 609, 428, 423, 351, 333, 330, 315, 299, 198, 185, 30] },
	{ "s": "ЯРКОСТЬ", "p": [443, 198, 184, 1013, 880, 439, 433, 351, 1007, 727, 426, 347, 330, 985, 891, 799, 635, 604, 445, 432, 427, 386, 377, 348, 343, 333, 197, 194, 193, 138] },
	{ "s": "ЯРКОСТЬЮ", "p": [981, 427, 351] },
	{ "s": "ЯРКУЮ", "p": [333] },
	{ "s": "ЯРЛЫК", "p": [646, 642, 477] },
	{ "s": "ЯРЛЫКА", "p": [646] },
	{ "s": "ЯРЛЫКОВ", "p": [646, 21] },
	{ "s": "ЯРОСТИ", "p": [674] },
	{ "s": "ЯРОСТНО", "p": [673] },
	{ "s": "ЯРОСТЬ", "p": [795, 674] },
	{ "s": "ЯРУС", "p": [990, 305] },
	{ "s": "ЯРЧЕ", "p": [878, 807, 437, 433, 197, 193] },
	{ "s": "ЯСЕН", "p": [230] },
	{ "s": "ЯСНА", "p": [216, 70] },
	{ "s": "ЯСНАЯ", "p": [808] },
	{ "s": "ЯСНО", "p": [802, 999, 946, 910, 854, 807, 804, 799, 795, 677, 246, 81, 65, 63, 53, 44] },
	{ "s": "ЯСНОЙ", "p": [807] },
	{ "s": "ЯСНОСТИ", "p": [1043] },
	{ "s": "ЯСНУЮ", "p": [808] },
	{ "s": "ЯСНЫМ", "p": [276] },
	{ "s": "ЯХТУ", "p": [29] },
	{ "s": "ЯЧЕЕК", "p": [799, 786, 779, 662, 660, 794, 738, 669, 795, 792, 791, 642, 30, 878, 836, 826, 818, 808, 778, 767, 757, 752, 747, 739, 675, 426, 391] },
	{ "s": "ЯЧЕЙК", "p": [1037] },
	{ "s": "ЯЧЕЙКА", "p": [799, 738, 700, 794, 778, 755, 740, 739, 679, 677, 669, 660, 380, 148, 65] },
	{ "s": "ЯЧЕЙКАМ", "p": [739] },
	{ "s": "ЯЧЕЙКАМИ", "p": [799, 779, 757, 739, 669, 662] },
	{ "s": "ЯЧЕЙКАХ", "p": [799, 769, 757, 747] },
	{ "s": "ЯЧЕЙКЕ", "p": [679, 171, 1009, 891, 799, 794, 786, 769, 755, 740, 1012, 802, 778, 767, 746, 745, 739, 738, 677, 662, 573, 380, 319, 170] },
	{ "s": "ЯЧЕЙКИ", "p": [739, 738, 799, 669, 660, 786, 794, 808, 778, 777, 767, 755, 752, 740, 795, 753, 700, 679, 677, 657, 1013, 788, 775, 747, 745, 704, 699, 668, 662, 637, 584, 575, 573, 506, 310, 273, 261, 235, 70, 68, 65] },
	{ "s": "ЯЧЕЙКИ\\ТЕКСТУР\\ОБЪЕКТОВ", "p": [799] },
	{ "s": "ЯЧЕЙКУ", "p": [740, 739, 738, 778, 794, 416, 836, 802, 799, 795, 757, 755, 753, 700, 677, 669, 660, 657, 535, 506, 235, 79] },
	{ "s": "ЯЩЕРИЦАМИ", "p": [467] },
	{ "s": "ЯЩИК", "p": [206, 592, 576] },
	{ "s": "ЯЩИКА", "p": [801, 624] },
	{ "s": "ЯЩИКАХ", "p": [660] },
	{ "s": "ЯЩИКЕ", "p": [576] },
	{ "s": "ЯЩИКИ", "p": [960, 391] },
	{ "s": "ЯЩИКОВ", "p": [660, 761, 98] }
]